dtools/tuples/__init__.py
dtools/tuples/ftuple.py
dtools/tuples/py.typed
dtools_tuples-0.27.1.dist-info/licenses/LICENSE
dtools_tuples-0.27.1.dist-info/WHEEL
dtools_tuples-0.27.1.dist-info/METADATA
dtools_tuples-0.27.1.dist-info/RECORD
