Metadata-Version: 2.4
Name: dtools.tuples
Version: 0.27.1
Summary: ### Developer Tools - Tuple-like data structures
Keywords: tuple,functional,ftuple,FTuple
Author-email: "Geoffrey R. Scheller" <geoffrey@scheller.com>
Requires-Python: >=3.12
Classifier: Development Status :: 4 - Beta
Classifier: Framework :: Pytest
Classifier: Intended Audience :: Developers
Classifier: License :: OSI Approved :: Apache Software License
Classifier: Operating System :: OS Independent
Classifier: Programming Language :: Python :: 3.13
Classifier: Typing :: Typed
License-File: LICENSE
Requires-Dist: dtools.fp >= 1.7.0, < 1.8
Requires-Dist: pytest >=8.3.5 ; extra == "test"
Requires-Dist: dtools.queues >=1.0.0, < 1.1 ; extra == "test"
Requires-Dist: dtools.splitends >=0.28.0, < 0.29 ; extra == "test"
Project-URL: Changelog, https://github.com/grscheller/dtools-tuples/blob/main/CHANGELOG.md
Project-URL: Documentation, https://grscheller.github.io/dtools-docs/tuples
Project-URL: Source, https://github.com/grscheller/dtools-tuples
Provides-Extra: test
